Workbook

Sheet How to edit
A1: Museum Builder — game data
A2: This workbook is the single source of truth for the game. The game reads it at startup: edit, save, refresh the browser.
A4: Rules
A5: 1. Blue text = values you can edit. Black text = formulas, do not edit.
A6: 2. Do NOT rename sheets or column headers (row 1). The game looks them up by name.
A7: 3. To add an item/persona/zone: add a new row with a unique id (lowercase, underscores, no spaces).
A8: 4. 'requires' syntax: ids separated by ';' = ALL needed; ids separated by '|' = ANY one is enough. Example: route; braille_label|audio_description
A9: Special tokens: route = every segment from the entrance to the zone's route_segment exists (Route sheet); has_screen = the zone has a video screen.
A10: 5. 'reach' = which visitor attribute is needed to benefit (column names of the Personas sheet), or 'all'.
A11: 6. 'status' = placeholder until confirmed by an interview or source; then set to validated and fill 'source'.
A12: 7. After interviews, change numbers here — no code change and no Claude session needed.
A14: Sheets
... A26: 16. Lighting (29.10): in a zone with lighting, a low-vision visitor gets better text (large-print label), a better view of the exhibit (exhibit_view) and easier paths (Scoring: lighting_reach_factor). Blind visitors get nothing from it.

Sheet Settings
A1: setting | B1: value | C1: meaning
A2: budget_eur | B2: 10000 | C2: Budget per round. Example value — change freely.
A3: rounds | B3: 2 | C3: Number of rounds per session
A4: catalogue_cost_if_everywhere_eur | B4: =SUM(Items!M2:M200) -> 27020 | C4: Formula: cost of placing every item everywhere
A5: budget_coverage | B5: =IFERROR(B2/B4,0) -> 0.37009623 | C5: Formula: share of the full catalogue the budget can buy. Aim ~30–50% so trade-offs are forced.

Sheet Items
A1: id | B1: name | C1: scope | D1: channel | E1: requires | F1: enhances | G1: reach | H1: info_value | I1: cost_eur | J1: status | K1: source | L1: units_if_everywhere | M1: cost_if_everywhere_eur | N1: name_fi | O1: enhance_factor | P1: validated_by | Q1: reach_grant
A2: tactile_route | B2: Tactile floor route (per segment) | C2: path | D2: tactile | G2: all | I2: 300 | J2: placeholder | K2: Smithsonian Guidelines: circulation route well lit, clearly defined, easy to follow | L2: =IF(C2="zone",COUNTA(Zones!$A$2:$A$50),IF(C2="path",COUNTIF(Route!$D$2:$D$100,FALSE()),1)) -> 4 | M2: =I2*L2 -> 1200 | N2: Kohokuvioitu opaslinja (osuus)
A3: braille_label | B3: Braille label | C3: zone | D3: braille | E3: route | G3: readsBraille | H3: 1 | I3: 120 | J3: placeholder | K3: Smithsonian: labels in consistent, predictable locations; Terhi: braille reaches only a fraction of VI visitors | L3: =IF(C3="zone",COUNTA(Zones!$A$2:$A$50),IF(C3="path",COUNTIF(Route!$D$2:$D$100,FALSE()),1)) -> 6 | M3: =I3*L3 -> 720 | N3: Pistekirjoitusteksti
A4: large_print_label | B4: Large-print, high-contrast label | C4: zone | D4: visual_enhanced | G4: residualVision | H4: 0.7 | I4: 80 | J4: placeholder | K4: Smithsonian: minimise glare for legibility; Terhi: font size, font, contrast | L4: =IF(C4="zone",COUNTA(Zones!$A$2:$A$50),IF(C4="path",COUNTIF(Route!$D$2:$D$100,FALSE()),1)) -> 6 | M4: =I4*L4 -> 480 | N4: Isokirjaiminen, kontrastinen teksti
A5: audio_description | B5: Audio description (content, per zone) | C5: zone | D5: audio | E5: audio_guide_devices|smartphone_audio | G5: all | H5: 1 | I5: 300 | J5: placeholder | K5: Smithsonian: audio description incl. label text; Terhi: audio beats braille | L5: =IF(C5="zone",COUNTA(Zones!$A$2:$A$50),IF(C5="path",COUNTIF(Route!$D$2:$D$100,FALSE()),1)) -> 6 | M5: =I5*L5 -> 1800 | N5: Kuvailutulkkaus (ääni, kohdekohtainen)
A6: audio_guide_devices | B6: Audio guide devices (venue) | C6: venue | D6: audio | G6: all | I6: 1000 | J6: placeholder | K6: Smithsonian: equipment available and signposted at entrance; Terhi: most common tool in Helsinki museums | L6: =IF(C6="zone",COUNTA(Zones!$A$2:$A$50),IF(C6="path",COUNTIF(Route!$D$2:$D$100,FALSE()),1)) -> 1 | M6: =I6*L6 -> 1000 | N6: Audio-opaslaitteet
A7: smartphone_audio | B7: Smartphone audio via QR/NFC + Wi-Fi (venue) | C7: venue | D7: audio | G7: usesSmartphone | I7: 600 | J7: placeholder | K7: Terhi: visitors with smartphones use apps (e.g. Be My Eyes) | L7: =IF(C7="zone",COUNTA(Zones!$A$2:$A$50),IF(C7="path",COUNTIF(Route!$D$2:$D$100,FALSE()),1)) -> 1 | M7: =I7*L7 -> 600 | N7: Ääniopastus älypuhelimeen (QR/NFC)
A8: tactile_replica | B8: Tactile replica | C8: zone | D8: tactile | E8: route; braille_label|audio_description | G8: comfortableWithTouch | H8: 0.8 | I8: 700 | J8: placeholder | K8: Smithsonian: touch + audio description; Terhi: touch must be complementary, not everyone is comfortable touching | L8: =IF(C8="zone",COUNTA(Zones!$A$2:$A$50),IF(C8="path",COUNTIF(Route!$D$2:$D$100,FALSE()),1)) -> 6 | M8: =I8*L8 -> 4200 | N8: Kosketeltava jäljennös
A9: touch_permission | B9: Touch permission on originals | C9: zone | D9: tactile | E9: staff_training | G9: comfortableWithTouch | H9: 0.8 | I9: 100 | J9: placeholder | K9: assumption (needs conservation approval) | L9: =IF(C9="zone",COUNTA(Zones!$A$2:$A$50),IF(C9="path",COUNTIF(Route!$D$2:$D$100,FALSE()),1)) -> 6 | M9: =I9*L9 -> 600 | N9: Kosketuslupa alkuperäisiin
A10: lighting | B10: Lighting upgrade | C10: zone | F10: large_print_label; exhibit_view | G10: all | I10: 400 | J10: placeholder | K10: Smithsonian circulation-route guideline; also affects low-vision reach (Scoring: lighting_reach_factor). Team decision 29.10.2026: lighting matters for text, exhibits and paths | L10: =IF(C10="zone",COUNTA(Zones!$A$2:$A$50),IF(C10="path",COUNTIF(Route!$D$2:$D$100,FALSE()),1)) -> 6 | M10: =I10*L10 -> 2400 | N10: Valaistuksen parannus | O10: 1.3
A11: seating | B11: Seating | C11: zone | E11: route | G11: all | I11: 160 | J11: placeholder | K11: assumption | L11: =IF(C11="zone",COUNTA(Zones!$A$2:$A$50),IF(C11="path",COUNTIF(Route!$D$2:$D$100,FALSE()),1)) -> 6 | M11: =I11*L11 -> 960 | N11: Istuimet
A12: staff_training | B12: Staff training (venue) | C12: venue | D12: human | G12: all | I12: 800 | J12: placeholder | K12: Fortuna et al. (2023): insufficient staff training is a key barrier | L12: =IF(C12="zone",COUNTA(Zones!$A$2:$A$50),IF(C12="path",COUNTIF(Route!$D$2:$D$100,FALSE()),1)) -> 1 | M12: =I12*L12 -> 800 | N12: Henkilökunnan koulutus
A13: guided_touch_tour | B13: Guided touch tour (scheduled times only) | C13: venue | D13: human | E13: staff_training; tactile_replica|touch_permission | G13: all | H13: 0.6 | I13: 500 | J13: placeholder | K13: Argyropoulos & Kanari (2015); Terhi: guided tours only at certain times | L13: =IF(C13="zone",COUNTA(Zones!$A$2:$A$50),IF(C13="path",COUNTIF(Route!$D$2:$D$100,FALSE()),1)) -> 1 | M13: =I13*L13 -> 500 | N13: Opastettu kosketuskierros | Q13: staff_guided
A14: audio_described_video | B14: Audio-described video | C14: zone | D14: audio | E14: has_screen; audio_guide_devices|smartphone_audio | G14: all | H14: 0.5 | I14: 400 | J14: placeholder | K14: Terhi: films with simultaneous audio description work well | L14: =IF(C14="zone",COUNTA(Zones!$A$2:$A$50),IF(C14="path",COUNTIF(Route!$D$2:$D$100,FALSE()),1)) -> 6 | M14: =I14*L14 -> 2400 | N14: Kuvailutulkattu video
A15: large_print_catalogue | B15: Large-print take-away catalogue (venue) | C15: venue | D15: visual_enhanced | G15: residualVision | H15: 0.5 | I15: 300 | J15: placeholder | K15: Terhi: take-away catalogues — readable font size and materials | L15: =IF(C15="zone",COUNTA(Zones!$A$2:$A$50),IF(C15="path",COUNTIF(Route!$D$2:$D$100,FALSE()),1)) -> 1 | M15: =I15*L15 -> 300 | N15: Isokirjaiminen esite
A16: braille_catalogue | B16: Braille catalogue (venue) | C16: venue | D16: braille | G16: readsBraille | H16: 0.5 | I16: 1200 | J16: placeholder | K16: Terhi: expensive and still excludes most VI visitors | L16: =IF(C16="zone",COUNTA(Zones!$A$2:$A$50),IF(C16="path",COUNTIF(Route!$D$2:$D$100,FALSE()),1)) -> 1 | M16: =I16*L16 -> 1200 | N16: Pistekirjoitusesite
A17: website_info | B17: Accessible pre-visit website info (venue) | C17: venue | D17: digital | G17: all | I17: 400 | J17: placeholder | K17: Argyropoulos & Kanari (2015): websites facilitate or hinder access | L17: =IF(C17="zone",COUNTA(Zones!$A$2:$A$50),IF(C17="path",COUNTIF(Route!$D$2:$D$100,FALSE()),1)) -> 1 | M17: =I17*L17 -> 400 | N17: Saavutettava ennakkotieto verkkosivuilla
A18: robot_guide | B18: Conversational AI robot guide (venue) | C18: venue | D18: audio | E18: staff_training | G18: all | H18: 0.4 | I18: 5000 | J18: placeholder | K18: Terhi interview notes (ambiguous: 'high cost low value') — validate | L18: =IF(C18="zone",COUNTA(Zones!$A$2:$A$50),IF(C18="path",COUNTIF(Route!$D$2:$D$100,FALSE()),1)) -> 1 | M18: =I18*L18 -> 5000 | N18: Keskusteleva tekoälyrobottiopas
A19: visitor_wifi | B19: Visitor Wi-Fi (venue) | C19: venue | G19: usesSmartphone | I19: 300 | J19: placeholder | K19: Terhi: visitors use their own AI apps (e.g. Be My Eyes) — they need connectivity | L19: =IF(C19="zone",COUNTA(Zones!$A$2:$A$50),IF(C19="path",COUNTIF(Route!$D$2:$D$100,FALSE()),1)) -> 1 | M19: =I19*L19 -> 300 | N19: Vierailijoiden Wi-Fi
A20: camera_readable_label | B20: Camera-readable label (for visitors' AI apps) | C20: zone | D20: audio | E20: visitor_wifi | G20: usesSmartphone | H20: 0.6 | I20: 60 | J20: placeholder | K20: Terhi: smartphone users point Be My Eyes / AI apps at labels and objects | L20: =IF(C20="zone",COUNTA(Zones!$A$2:$A$50),IF(C20="path",COUNTIF(Route!$D$2:$D$100,FALSE()),1)) -> 6 | M20: =I20*L20 -> 360 | N20: Sovelluksella luettava teksti
A21: reference_numbering | B21: Clear numbering linking object, label and audio | C21: zone | F21: audio_description; braille_label; large_print_label | G21: all | I21: 50 | J21: placeholder | K21: Terhi: clear references to descriptions (cognitive accessibility) | L21: =IF(C21="zone",COUNTA(Zones!$A$2:$A$50),IF(C21="path",COUNTIF(Route!$D$2:$D$100,FALSE()),1)) -> 6 | M21: =I21*L21 -> 300 | N21: Selkeä numerointi (kohde–teksti–ääni) | O21: 1.15
A22: tactile_floor_plan | B22: Tactile floor plan at entrance (braille + raised lines) | C22: venue | D22: tactile | G22: all | I22: 1500 | J22: placeholder | K22: Seen at Postimuseo visit 26.10.2026 (photo IMG_3967); Smithsonian: give the big picture up front | L22: =IF(C22="zone",COUNTA(Zones!$A$2:$A$50),IF(C22="path",COUNTIF(Route!$D$2:$D$100,FALSE()),1)) -> 1 | M22: =I22*L22 -> 1500 | N22: Kohokartta sisäänkäynnillä | Q22: plan_only
A23: exhibit_view | B23: Exhibit itself can be looked at (existing display) | C23: zone | D23: visual | G23: residualVision | H23: 0.3 | I23: 0 | J23: placeholder | K23: assumption — low-vision visitors get some information from seeing the object; lighting improves it. VALIDATE with VI reviewer | L23: =IF(C23="zone",COUNTA(Zones!$A$2:$A$50),IF(C23="path",COUNTIF(Route!$D$2:$D$100,FALSE()),1)) -> 6 | M23: =I23*L23 -> 0 | N23: Esinettä voi katsoa (olemassa oleva esillepano)

Sheet Personas
A1: id | B1: name | C1: readsBraille | D1: usesSmartphone | E1: residualVision | F1: comfortableWithTouch | G1: visitorShare | H1: status | I1: source | J1: name_fi | K1: validated_by
A2: blind_non_braille | B2: Blind, does not read braille | C2: =FALSE() -> FALSE | D2: =TRUE() -> TRUE | E2: =FALSE() -> FALSE | F2: =TRUE() -> TRUE | G2: 0.5 | H2: placeholder | I2: Terhi: braille only reaches a fragment of VI people | J2: Sokea, ei lue pistekirjoitusta
A3: blind_braille | B3: Blind, reads braille | C3: =TRUE() -> TRUE | D3: =FALSE() -> FALSE | E3: =FALSE() -> FALSE | F3: =TRUE() -> TRUE | G3: 0.2 | H3: placeholder | J3: Sokea, lukee pistekirjoitusta
A4: low_vision | B4: Low vision | C4: =FALSE() -> FALSE | D4: =TRUE() -> TRUE | E4: =TRUE() -> TRUE | F4: =FALSE() -> FALSE | G4: 0.3 | H4: placeholder | I4: Terhi: font size, contrast; not everyone is comfortable touching | J4: Heikkonäköinen
F6: Total share (should be 100%) | G6: =SUM(G2:G4) -> 1

Sheet Zones
A1: id | B1: name_fi | C1: name_en | D1: has_screen | E1: exhibit_objects | F1: route_segment | G1: notes | H1: exhibits (names, ';'-separated) | I1: exhibits_fi
A2: viestinta | B2: Viestintä | C2: Communication | D2: =FALSE() -> FALSE | E2: 2 | F2: s1
A3: alypuhelin | B3: Älypuhelin | C3: Smartphone | D3: =TRUE() -> TRUE | E3: 2 | F3: s2
A4: verkot | B4: Verkot | C4: Networks | D4: =FALSE() -> FALSE | E4: 2 | F4: s3
A5: kirjeet_paketit | B5: Kirjeet ja paketit | C5: Letters and parcels | D5: =FALSE() -> FALSE | E5: 2 | F5: s7
A6: lajittelu | B6: Lajittelu | C6: Sorting | D6: =FALSE() -> FALSE | E6: 1 | F6: s6 | G6: Existing seating nearby
A7: historia | B7: Historia ja nykypäivä | C7: History and present day | D7: =TRUE() -> TRUE | E7: 2 | F7: s5

Sheet Route
A1: segment_id | B1: from | C1: description | D1: existing | E1: notes | F1: validated_by
A2: s1 | B2: entrance | C2: Entrance hall → Viestintä (south room) | D2: =TRUE() -> TRUE | E2: Dashed guidance line on tactile plan — verify with Olli
A3: s2 | B3: s1 | C3: Viestintä → Älypuhelin island | D3: =TRUE() -> TRUE | E3: Verify
A4: s3 | B4: s2 | C4: Älypuhelin → Verkot | D4: =TRUE() -> TRUE | E4: Verify
A5: s4 | B5: s3 | C5: Verkot → east corridor junction | D5: =FALSE() -> FALSE
A6: s5 | B6: s4 | C6: Junction → Historia ja nykypäivä | D6: =FALSE() -> FALSE
A7: s6 | B7: s5 | C7: Historia → Lajittelu | D7: =FALSE() -> FALSE
A8: s7 | B8: s6 | C8: Lajittelu → Kirjeet ja paketit | D8: =FALSE() -> FALSE

Sheet Existing
A1: item_id | B1: zone_id | C1: notes | D1: validated_by
A2: tactile_floor_plan | C2: At entrance (venue-level). Seen on visit 26.10.
A3: seating | B3: lajittelu | C3: Seating area next to Lajittelu on the tactile plan
A4: exhibit_view | B4: viestinta | C4: Baseline: the object can be looked at. Assumption to validate.
A5: exhibit_view | B5: alypuhelin | C5: Baseline: the object can be looked at. Assumption to validate.
A6: exhibit_view | B6: verkot | C6: Baseline: the object can be looked at. Assumption to validate.
A7: exhibit_view | B7: kirjeet_paketit | C7: Baseline: the object can be looked at. Assumption to validate.
A8: exhibit_view | B8: lajittelu | C8: Baseline: the object can be looked at. Assumption to validate.
A9: exhibit_view | B9: historia | C9: Baseline: the object can be looked at. Assumption to validate.

Sheet Scoring
A1: parameter | B1: value | C1: meaning
A2: reach_full | B2: 1 | C2: Zone reachable by continuous tactile route from the entrance
A3: reach_staff_guided | B3: 0.6 | C3: Reachable only with staff help (needs staff_training + guided_touch_tour)
A4: reach_plan_only | B4: 0.3 | C4: Only the entrance floor plan orients the visitor
A5: richness_per_extra_channel | B5: 0.2 | C5: Bonus per additional distinct usable channel in a zone
A6: richness_cap | B6: 0.4 | C6: Maximum richness bonus
A7: min_channels_full_value | B7: 2 | C7: Channels a persona needs in a zone for full value (multimodal redundancy)
A8: single_channel_penalty | B8: 0.8 | C8: Multiplier when a persona has only one usable channel in a zone
A9: lighting_reach_factor | B9: 1.3 | C9: Multiplier on reach for visitors with residual vision in a zone that has lighting (capped at 1.0): lit paths are easier to follow

Sheet Texts
A1: key | B1: en | C1: fi | D1: validated_by
A2: app_title | B2: Museum Builder | C2: Museorakentaja
A3: challenge | B3: You have {budget} to make this exhibition work for visitors with visual impairment. | C3: Sinulla on {budget}, jotta näyttely toimisi näkövammaisille kävijöille.
A4: budget | B4: Budget | C4: Budjetti
A5: remaining | B5: Remaining | C5: Jäljellä
A6: catalogue | B6: Catalogue | C6: Valikoima
A7: room_view | B7: Room (text view) | C7: Huone (tekstinäkymä)
A8: place | B8: Place | C8: Sijoita
A9: remove | B9: Remove | C9: Poista
A10: requires | B10: Needs | C10: Vaatii
A11: helps | B11: Helps | C11: Auttaa
A12: cost | B12: Cost | C12: Hinta
A13: zone | B13: Zone | C13: Alue
... A47: ch_visual | B47: looks at the exhibit | C47: katsoo esinettä
